POSPair/NLP_POSPair.py
POSPair/__init__.py
POSPair-0.0.4.dist-info/LICENSE.txt
POSPair-0.0.4.dist-info/METADATA
POSPair-0.0.4.dist-info/WHEEL
POSPair-0.0.4.dist-info/top_level.txt
POSPair-0.0.4.dist-info/RECORD
