Metadata-Version: 2.1
Name: POSPair
Version: 0.0.4
Summary: Simplifying representation for natural language processing
Home-page: https://github.com/jmacwan/POSPair
Author: Jim Macwan
Author-email: jimmacwan94@gmail.com
License: UNKNOWN
Platform: UNKNOWN
Classifier: Programming Language :: Python :: 3
Classifier: License :: OSI Approved :: GNU General Public License v3 (GPLv3)
Classifier: Operating System :: OS Independent
Requires-Dist: pycorenlp
Requires-Dist: POSPairWordEmbeddings
